inference_server/__init__.py
inference_server/_plugin.py
inference_server/default_plugin.py
inference_server/py.typed
inference_server/testing.py
inference_server-1.3.3.dist-info/licenses/LICENSE
inference_server-1.3.3.dist-info/licenses/LICENSE_HEADER.txt
inference_server-1.3.3.dist-info/METADATA
inference_server-1.3.3.dist-info/WHEEL
inference_server-1.3.3.dist-info/top_level.txt
inference_server-1.3.3.dist-info/RECORD
