Metadata-Version: 2.4
Name: inference-server
Version: 1.3.3
Summary: Deploy your AI/ML model to Amazon SageMaker for Real-Time Inference and Batch Transform using your own Docker container image.
Author-email: "J.P. Morgan Chase & Co." <open_source@jpmorgan.com>
License:                                  Apache License
Project-URL: Homepage, https://github.com/jpmorganchase/inference-server
Project-URL: Bug Tracker, https://github.com/jpmorganchase/inference-server/issues
Project-URL: Documentation, https://inference-server.readthedocs.io
Project-URL: Download, https://pypi.python.org/pypi/inference-server
Project-URL: Source Code, https://github.com/jpmorganchase/inference-server
Keywords: artificial-intelligence,docker,http-server,inference,jpmorganchase,machine-learning,python,sagemaker,wsgi-server
Classifier: Development Status :: 5 - Production/Stable
Classifier: License :: OSI Approved :: Apache Software License
Classifier: Operating System :: OS Independent
Classifier: Programming Language :: Python :: 3
Classifier: Typing :: Typed
Requires-Python: >=3.8
License-File: LICENSE
License-File: LICENSE_HEADER.txt
Requires-Dist: botocore
Requires-Dist: codetiming~=1.4
Requires-Dist: orjson~=3.0
Requires-Dist: pluggy~=1.0
Requires-Dist: werkzeug~=3.0
Provides-Extra: docs
Requires-Dist: pytest; extra == "docs"
Requires-Dist: sphinx; extra == "docs"
Requires-Dist: sphinx-rtd-theme; extra == "docs"
Provides-Extra: testing
Requires-Dist: pytest; extra == "testing"
Requires-Dist: pytest-cov; extra == "testing"
Provides-Extra: linting
Requires-Dist: black; extra == "linting"
Requires-Dist: flake8; extra == "linting"
Requires-Dist: interrogate; extra == "linting"
Requires-Dist: isort; extra == "linting"
Requires-Dist: mypy; extra == "linting"
Requires-Dist: pre-commit; extra == "linting"
Requires-Dist: pytest; extra == "linting"
Dynamic: license-file
